README.txt
setup.py
SupervisorAdmin.egg-info/PKG-INFO
SupervisorAdmin.egg-info/SOURCES.txt
SupervisorAdmin.egg-info/dependency_links.txt
SupervisorAdmin.egg-info/entry_points.txt
SupervisorAdmin.egg-info/not-zip-safe
SupervisorAdmin.egg-info/top_level.txt
supervisoradmin/__init__.py
supervisoradmin/add.py