Metadata-Version: 1.0
Name: SupervisorAdmin
Version: 0.1
Summary: add supervisor jobs
Home-page: http://k0s.org/hg/SupervisorAdmin
Author: Jeff Hammel
Author-email: k0scist@gmail.com
License: UNKNOWN
Platform: UNKNOWN
